grep_ips/__init__.py
grep_ips/grep_ips.py
grep_ips/grep_ips_test.py
myorigin/__init__.py
myorigin/flock_data.py
myorigin/myorigin.py
myorigin/myorigin_test.py
myorigin/parrots.py
myorigin-0.4.0.dist-info/LICENSE
myorigin-0.4.0.dist-info/METADATA
myorigin-0.4.0.dist-info/WHEEL
myorigin-0.4.0.dist-info/entry_points.txt
myorigin-0.4.0.dist-info/top_level.txt
myorigin-0.4.0.dist-info/RECORD
