Metadata-Version: 2.1
Name: myorigin
Version: 0.4.0
Summary: Fast, fault-tolerant public IP address retrieval from Python or CLI.
Home-page: https://github.com/bitinerant/myorigin
Author: bitinerant
Author-email: bitinerant@users.noreply.github.com
Project-URL: Bug Tracker, https://github.com/bitinerant/myorigin/issues
Classifier: Programming Language :: Python :: 3
Classifier: License :: OSI Approved :: GNU General Public License v3 (GPLv3)
Classifier: Operating System :: OS Independent
Requires-Python: >=3.6
License-File: LICENSE
Requires-Dist: aiohttp
Requires-Dist: sqlmodel
Requires-Dist: platformdirs
Requires-Dist: pytest
